<annotation>
	<folder>images</folder>
	<filename>ima152.png</filename>
	<path>C:\Users\quan nguyen\TensorFlow\workspace\training_demo\images\ima152.png</path>
	<source>
		<database>Unknown</database>
	</source>
	<size>
		<width>1920</width>
		<height>1080</height>
		<depth>3</depth>
	</size>
	<segmented>0</segmented>
	<object>
		<name>t</name>
		<pose>Unspecified</pose>
		<truncated>0</truncated>
		<difficult>0</difficult>
		<bndbox>
			<xmin>850</xmin>
			<ymin>464</ymin>
			<xmax>1069</xmax>
			<ymax>983</ymax>
		</bndbox>
	</object>
	<object>
		<name>t</name>
		<pose>Unspecified</pose>
		<truncated>0</truncated>
		<difficult>0</difficult>
		<bndbox>
			<xmin>1086</xmin>
			<ymin>316</ymin>
			<xmax>1165</xmax>
			<ymax>508</ymax>
		</bndbox>
	</object>
</annotation>
